Metadata-Version: 2.1
Name: thpham-cdktf-provider-openstack
Version: 1.0.0
Summary: Prebuilt openstack Provider for Terraform CDK (cdktf)
Home-page: https://github.com/thpham/cdktf-provider-openstack.git
Author: thpham
License: MPL-2.0
Project-URL: Source, https://github.com/thpham/cdktf-provider-openstack.git
Classifier: Intended Audience :: Developers
Classifier: Operating System :: OS Independent
Classifier: Programming Language :: JavaScript
Classifier: Programming Language :: Python :: 3 :: Only
Classifier: Programming Language :: Python :: 3.8
Classifier: Programming Language :: Python :: 3.9
Classifier: Programming Language :: Python :: 3.10
Classifier: Programming Language :: Python :: 3.11
Classifier: Typing :: Typed
Classifier: Development Status :: 4 - Beta
Classifier: License :: OSI Approved
Requires-Python: ~=3.8
License-File: LICENSE
Requires-Dist: cdktf <0.21.0,>=0.20.0
Requires-Dist: constructs <11.0.0,>=10.3.0
Requires-Dist: jsii <2.0.0,>=1.95.0
Requires-Dist: publication >=0.0.3
Requires-Dist: typeguard ~=2.13.3
